mtkresearch/__init__.py
mtkresearch/llm/__init__.py
mtkresearch/llm/chat.py
mtkresearch/llm/image_process_v3.py
mtkresearch/llm/prompt.py
mtkresearch-0.3.2.dist-info/METADATA
mtkresearch-0.3.2.dist-info/WHEEL
mtkresearch-0.3.2.dist-info/top_level.txt
mtkresearch-0.3.2.dist-info/RECORD
